timezones_cli/__init__.py
timezones_cli/main.py
timezones_cli/commands/__init__.py
timezones_cli/commands/add.py
timezones_cli/commands/remove.py
timezones_cli/commands/search.py
timezones_cli/commands/select.py
timezones_cli/commands/show.py
timezones_cli/commands/utc.py
timezones_cli/utils/__init__.py
timezones_cli/utils/abbreviations.py
timezones_cli/utils/validators.py
timezones_cli/utils/variables.py
timezones_cli-0.3.8.dist-info/LICENCE
timezones_cli-0.3.8.dist-info/METADATA
timezones_cli-0.3.8.dist-info/WHEEL
timezones_cli-0.3.8.dist-info/entry_points.txt
timezones_cli-0.3.8.dist-info/top_level.txt
timezones_cli-0.3.8.dist-info/RECORD
