Metadata-Version: 2.2
Name: timezones_cli
Version: 0.3.8
Summary: Get local datetime from multiple timezones!
Author: Yankee Maharjan
License: MIT
Project-URL: homepage, https://github.com/yankeexe/timezones-cli
Classifier: Programming Language :: Python :: 3.9
Classifier: Programming Language :: Python :: 3.10
Classifier: Programming Language :: Python :: 3.11
Classifier: Operating System :: OS Independent
Classifier: License :: OSI Approved :: MIT License
License-File: LICENCE
Requires-Dist: click==8.1.5
Requires-Dist: tabulate==0.9.0
Requires-Dist: rich<=7.1.0
Requires-Dist: pycountry==22.3.5
Requires-Dist: pytz
Requires-Dist: simple-term-menu==1.6.1
Requires-Dist: tzlocal==2.1
Requires-Dist: thefuzz[speedup]
Provides-Extra: dev
Requires-Dist: pytest>=6.2.5; extra == "dev"
Requires-Dist: black<=20.8b1; extra == "dev"
Requires-Dist: pre-commit; extra == "dev"
Requires-Dist: mypy; extra == "dev"
Requires-Dist: freezegun; extra == "dev"
Requires-Dist: flake8; extra == "dev"
Requires-Dist: types-pytz; extra == "dev"
Requires-Dist: types-tzlocal; extra == "dev"
Requires-Dist: types-tabulate; extra == "dev"
